nlweb_core/NLWebRankingHandler.py
nlweb_core/NLWebVectorDBRankingHandler.py
nlweb_core/__init__.py
nlweb_core/baseNLWeb.py
nlweb_core/config.py
nlweb_core/embedding.py
nlweb_core/llm.py
nlweb_core/mcp_handler.py
nlweb_core/ranking.py
nlweb_core/retriever.py
nlweb_core/simple_server.py
nlweb_core/utils.py
nlweb_core/protocol/__init__.py
nlweb_core/protocol/models.py
nlweb_core/query_analysis/__init__.py
nlweb_core/query_analysis/query_analysis.py
nlweb_core-0.5.42.dist-info/METADATA
nlweb_core-0.5.42.dist-info/WHEEL
nlweb_core-0.5.42.dist-info/top_level.txt
nlweb_core-0.5.42.dist-info/RECORD
