Metadata-Version: 2.4
Name: nlweb-core
Version: 0.5.42
Summary: Core framework for NLWeb - Natural Language Web interface with config-driven provider architecture
Author: Microsoft Corporation
License: MIT
Project-URL: Homepage, https://github.com/microsoft/NLWeb_Core
Project-URL: Documentation, https://github.com/microsoft/NLWeb_Core/blob/main/README.md
Project-URL: Repository, https://github.com/microsoft/NLWeb_Core
Project-URL: Issues, https://github.com/microsoft/NLWeb_Core/issues
Classifier: Development Status :: 4 - Beta
Classifier: Intended Audience :: Developers
Classifier: License :: OSI Approved :: MIT License
Classifier: Programming Language :: Python :: 3
Classifier: Programming Language :: Python :: 3.9
Classifier: Programming Language :: Python :: 3.10
Classifier: Programming Language :: Python :: 3.11
Classifier: Programming Language :: Python :: 3.12
Requires-Python: >=3.9
Requires-Dist: pyyaml>=6.0
Requires-Dist: python-dotenv>=1.0.0
Requires-Dist: aiohttp>=3.8.0
Provides-Extra: dev
Requires-Dist: pytest>=7.0; extra == "dev"
Requires-Dist: pytest-asyncio>=0.21.0; extra == "dev"
Requires-Dist: black>=23.0; extra == "dev"
Requires-Dist: mypy>=1.0; extra == "dev"
